yaenv/__init__.py
yaenv/core.py
yaenv/db.py
yaenv/email.py
yaenv/py.typed
yaenv/utils.py
yaenv-1.6.4.dist-info/LICENSE
yaenv-1.6.4.dist-info/METADATA
yaenv-1.6.4.dist-info/WHEEL
yaenv-1.6.4.dist-info/RECORD
