Metadata-Version: 2.1
Name: yaenv
Version: 1.6.4
Summary: Yet another dotenv parser for Python.
Home-page: https://github.com/ObserverOfTime/yaenv
License: BSD-3-Clause
Keywords: 12factor,config,configuration,django,dotenv,environment,variables
Author: ObserverOfTime
Author-email: chronobserver@disroot.org
Requires-Python: >=3.10,<4.0
Classifier: Development Status :: 5 - Production/Stable
Classifier: Intended Audience :: Developers
Classifier: License :: OSI Approved :: BSD License
Classifier: Natural Language :: English
Classifier: Operating System :: OS Independent
Classifier: Programming Language :: Python
Classifier: Programming Language :: Python :: 3
Classifier: Programming Language :: Python :: 3.10
Classifier: Programming Language :: Python :: 3.11
Classifier: Programming Language :: Python :: 3 :: Only
Classifier: Topic :: Software Development :: Libraries :: Python Modules
Classifier: Typing :: Typed
Project-URL: Bug tracker, https://github.com/ObserverOfTime/yaenv/issues
Project-URL: Documentation, https://yaenv.readthedocs.io
Project-URL: Donations, https://github.com/sponsors/ObserverOfTime
